KimariDraw/__init__.py
KimariDraw/kimaridraw.py
kimaridraw-2.5.2.5.dist-info/LICENSE
kimaridraw-2.5.2.5.dist-info/METADATA
kimaridraw-2.5.2.5.dist-info/WHEEL
kimaridraw-2.5.2.5.dist-info/entry_points.txt
kimaridraw-2.5.2.5.dist-info/top_level.txt
kimaridraw-2.5.2.5.dist-info/RECORD
