Metadata-Version: 2.1
Name: kimaridraw
Version: 2.5.2.5
Summary: A Python script that processes Multiwfn spectral data and plots various spectra.
Home-page: https://github.com/kimariyb/kimariDraw
Author: Kimariyb, Ryan Hsiun
Author-email: kimariyb@163.com
Classifier: Programming Language :: Python :: 3
Classifier: License :: OSI Approved :: MIT License
Classifier: Operating System :: OS Independent
Requires-Python: >=3.8
License-File: LICENSE
